apds9960/__init__.py
apds9960/const.py
apds9960/device.py
apds9960/exceptions.py
apds9960-0.3.0.dist-info/licenses/LICENSE
apds9960-0.3.0.dist-info/METADATA
apds9960-0.3.0.dist-info/WHEEL
apds9960-0.3.0.dist-info/top_level.txt
apds9960-0.3.0.dist-info/RECORD
