Metadata-Version: 2.4
Name: apds9960
Version: 0.3.0
Summary: Python APDS-9960 Library
Home-page: https://github.com/liske/python-apds9960/
Author: Thomas Liske
Author-email: thomas@fiasko-nw.net
License: GPLv3+
Keywords: apds9960
Classifier: Programming Language :: Python
Classifier: Programming Language :: Python :: 2
Classifier: Programming Language :: Python :: 3
Classifier: Topic :: Software Development :: Libraries :: Python Modules
License-File: LICENSE
Dynamic: author
Dynamic: author-email
Dynamic: classifier
Dynamic: description
Dynamic: description-content-type
Dynamic: home-page
Dynamic: keywords
Dynamic: license
Dynamic: license-file
Dynamic: summary
